README.rst
setup.py
fc_hypermesh/CartesianGrid.py
fc_hypermesh/EltMesh.py
fc_hypermesh/Hypercube.py
fc_hypermesh/Matplotlib.py
fc_hypermesh/OrthMesh.py
fc_hypermesh/__init__.py
fc_hypermesh/benchs.py
fc_hypermesh/demos.py
fc_hypermesh/utils.py
fc_hypermesh.egg-info/PKG-INFO
fc_hypermesh.egg-info/SOURCES.txt
fc_hypermesh.egg-info/dependency_links.txt
fc_hypermesh.egg-info/requires.txt
fc_hypermesh.egg-info/top_level.txt