Metadata-Version: 2.1
Name: fc-hypermesh
Version: 0.1.1
Summary: Generate conforming meshes of hypercubes, hyperrectangles or of any d-orthotopes by simplices or orthotopes with their m-faces
Home-page: http://www.math.univ-paris13.fr/~cuvelier/software
Author: Francois Cuvelier
Author-email: cuvelier@math.univ-paris13.fr
License: BSD
Platform: UNKNOWN
Classifier: Topic :: Scientific/Engineering :: Mathematics
